[
  {
    "archivo": "6 (4) 105-118.pdf",
    "fragmento_numero": 1,
    "total_fragments_archivo": 13
  },
  {
    "archivo": "6 (4) 105-118.pdf",
    "fragmento_numero": 2,
    "total_fragments_archivo": 13
  },
  {
    "archivo": "6 (4) 105-118.pdf",
    "fragmento_numero": 3,
    "total_fragments_archivo": 13
  },
  {
    "archivo": "6 (4) 105-118.pdf",
    "fragmento_numero": 4,
    "total_fragments_archivo": 13
  },
  {
    "archivo": "6 (4) 105-118.pdf",
    "fragmento_numero": 5,
    "total_fragments_archivo": 13
  },
  {
    "archivo": "6 (4) 105-118.pdf",
    "fragmento_numero": 6,
    "total_fragments_archivo": 13
  },
  {
    "archivo": "6 (4) 105-118.pdf",
    "fragmento_numero": 7,
    "total_fragments_archivo": 13
  },
  {
    "archivo": "6 (4) 105-118.pdf",
    "fragmento_numero": 8,
    "total_fragments_archivo": 13
  },
  {
    "archivo": "6 (4) 105-118.pdf",
    "fragmento_numero": 9,
    "total_fragments_archivo": 13
  },
  {
    "archivo": "6 (4) 105-118.pdf",
    "fragmento_numero": 10,
    "total_fragments_archivo": 13
  },
  {
    "archivo": "6 (4) 105-118.pdf",
    "fragmento_numero": 11,
    "total_fragments_archivo": 13
  },
  {
    "archivo": "6 (4) 105-118.pdf",
    "fragmento_numero": 12,
    "total_fragments_archivo": 13
  },
  {
    "archivo": "6 (4) 105-118.pdf",
    "fragmento_numero": 13,
    "total_fragments_archivo": 13
  },
  {
    "archivo": "642330522 (1).pdf",
    "fragmento_numero": 1,
    "total_fragments_archivo": 37
  },
  {
    "archivo": "642330522 (1).pdf",
    "fragmento_numero": 2,
    "total_fragments_archivo": 37
  },
  {
    "archivo": "642330522 (1).pdf",
    "fragmento_numero": 3,
    "total_fragments_archivo": 37
  },
  {
    "archivo": "642330522 (1).pdf",
    "fragmento_numero": 4,
    "total_fragments_archivo": 37
  },
  {
    "archivo": "642330522 (1).pdf",
    "fragmento_numero": 5,
    "total_fragments_archivo": 37
  },
  {
    "archivo": "642330522 (1).pdf",
    "fragmento_numero": 6,
    "total_fragments_archivo": 37
  },
  {
    "archivo": "642330522 (1).pdf",
    "fragmento_numero": 7,
    "total_fragments_archivo": 37
  },
  {
    "archivo": "642330522 (1).pdf",
    "fragmento_numero": 8,
    "total_fragments_archivo": 37
  },
  {
    "archivo": "642330522 (1).pdf",
    "fragmento_numero": 9,
    "total_fragments_archivo": 37
  },
  {
    "archivo": "642330522 (1).pdf",
    "fragmento_numero": 10,
    "total_fragments_archivo": 37
  },
  {
    "archivo": "642330522 (1).pdf",
    "fragmento_numero": 11,
    "total_fragments_archivo": 37
  },
  {
    "archivo": "642330522 (1).pdf",
    "fragmento_numero": 12,
    "total_fragments_archivo": 37
  },
  {
    "archivo": "642330522 (1).pdf",
    "fragmento_numero": 13,
    "total_fragments_archivo": 37
  },
  {
    "archivo": "642330522 (1).pdf",
    "fragmento_numero": 14,
    "total_fragments_archivo": 37
  },
  {
    "archivo": "642330522 (1).pdf",
    "fragmento_numero": 15,
    "total_fragments_archivo": 37
  },
  {
    "archivo": "642330522 (1).pdf",
    "fragmento_numero": 16,
    "total_fragments_archivo": 37
  },
  {
    "archivo": "642330522 (1).pdf",
    "fragmento_numero": 17,
    "total_fragments_archivo": 37
  },
  {
    "archivo": "642330522 (1).pdf",
    "fragmento_numero": 18,
    "total_fragments_archivo": 37
  },
  {
    "archivo": "642330522 (1).pdf",
    "fragmento_numero": 19,
    "total_fragments_archivo": 37
  },
  {
    "archivo": "642330522 (1).pdf",
    "fragmento_numero": 20,
    "total_fragments_archivo": 37
  },
  {
    "archivo": "642330522 (1).pdf",
    "fragmento_numero": 21,
    "total_fragments_archivo": 37
  },
  {
    "archivo": "642330522 (1).pdf",
    "fragmento_numero": 22,
    "total_fragments_archivo": 37
  },
  {
    "archivo": "642330522 (1).pdf",
    "fragmento_numero": 23,
    "total_fragments_archivo": 37
  },
  {
    "archivo": "642330522 (1).pdf",
    "fragmento_numero": 24,
    "total_fragments_archivo": 37
  },
  {
    "archivo": "642330522 (1).pdf",
    "fragmento_numero": 25,
    "total_fragments_archivo": 37
  },
  {
    "archivo": "642330522 (1).pdf",
    "fragmento_numero": 26,
    "total_fragments_archivo": 37
  },
  {
    "archivo": "642330522 (1).pdf",
    "fragmento_numero": 27,
    "total_fragments_archivo": 37
  },
  {
    "archivo": "642330522 (1).pdf",
    "fragmento_numero": 28,
    "total_fragments_archivo": 37
  },
  {
    "archivo": "642330522 (1).pdf",
    "fragmento_numero": 29,
    "total_fragments_archivo": 37
  },
  {
    "archivo": "642330522 (1).pdf",
    "fragmento_numero": 30,
    "total_fragments_archivo": 37
  },
  {
    "archivo": "642330522 (1).pdf",
    "fragmento_numero": 31,
    "total_fragments_archivo": 37
  },
  {
    "archivo": "642330522 (1).pdf",
    "fragmento_numero": 32,
    "total_fragments_archivo": 37
  },
  {
    "archivo": "642330522 (1).pdf",
    "fragmento_numero": 33,
    "total_fragments_archivo": 37
  },
  {
    "archivo": "642330522 (1).pdf",
    "fragmento_numero": 34,
    "total_fragments_archivo": 37
  },
  {
    "archivo": "642330522 (1).pdf",
    "fragmento_numero": 35,
    "total_fragments_archivo": 37
  },
  {
    "archivo": "642330522 (1).pdf",
    "fragmento_numero": 36,
    "total_fragments_archivo": 37
  },
  {
    "archivo": "642330522 (1).pdf",
    "fragmento_numero": 37,
    "total_fragments_archivo": 37
  },
  {
    "archivo": "642330522.pdf",
    "fragmento_numero": 1,
    "total_fragments_archivo": 37
  },
  {
    "archivo": "642330522.pdf",
    "fragmento_numero": 2,
    "total_fragments_archivo": 37
  },
  {
    "archivo": "642330522.pdf",
    "fragmento_numero": 3,
    "total_fragments_archivo": 37
  },
  {
    "archivo": "642330522.pdf",
    "fragmento_numero": 4,
    "total_fragments_archivo": 37
  },
  {
    "archivo": "642330522.pdf",
    "fragmento_numero": 5,
    "total_fragments_archivo": 37
  },
  {
    "archivo": "642330522.pdf",
    "fragmento_numero": 6,
    "total_fragments_archivo": 37
  },
  {
    "archivo": "642330522.pdf",
    "fragmento_numero": 7,
    "total_fragments_archivo": 37
  },
  {
    "archivo": "642330522.pdf",
    "fragmento_numero": 8,
    "total_fragments_archivo": 37
  },
  {
    "archivo": "642330522.pdf",
    "fragmento_numero": 9,
    "total_fragments_archivo": 37
  },
  {
    "archivo": "642330522.pdf",
    "fragmento_numero": 10,
    "total_fragments_archivo": 37
  },
  {
    "archivo": "642330522.pdf",
    "fragmento_numero": 11,
    "total_fragments_archivo": 37
  },
  {
    "archivo": "642330522.pdf",
    "fragmento_numero": 12,
    "total_fragments_archivo": 37
  },
  {
    "archivo": "642330522.pdf",
    "fragmento_numero": 13,
    "total_fragments_archivo": 37
  },
  {
    "archivo": "642330522.pdf",
    "fragmento_numero": 14,
    "total_fragments_archivo": 37
  },
  {
    "archivo": "642330522.pdf",
    "fragmento_numero": 15,
    "total_fragments_archivo": 37
  },
  {
    "archivo": "642330522.pdf",
    "fragmento_numero": 16,
    "total_fragments_archivo": 37
  },
  {
    "archivo": "642330522.pdf",
    "fragmento_numero": 17,
    "total_fragments_archivo": 37
  },
  {
    "archivo": "642330522.pdf",
    "fragmento_numero": 18,
    "total_fragments_archivo": 37
  },
  {
    "archivo": "642330522.pdf",
    "fragmento_numero": 19,
    "total_fragments_archivo": 37
  },
  {
    "archivo": "642330522.pdf",
    "fragmento_numero": 20,
    "total_fragments_archivo": 37
  },
  {
    "archivo": "642330522.pdf",
    "fragmento_numero": 21,
    "total_fragments_archivo": 37
  },
  {
    "archivo": "642330522.pdf",
    "fragmento_numero": 22,
    "total_fragments_archivo": 37
  },
  {
    "archivo": "642330522.pdf",
    "fragmento_numero": 23,
    "total_fragments_archivo": 37
  },
  {
    "archivo": "642330522.pdf",
    "fragmento_numero": 24,
    "total_fragments_archivo": 37
  },
  {
    "archivo": "642330522.pdf",
    "fragmento_numero": 25,
    "total_fragments_archivo": 37
  },
  {
    "archivo": "642330522.pdf",
    "fragmento_numero": 26,
    "total_fragments_archivo": 37
  },
  {
    "archivo": "642330522.pdf",
    "fragmento_numero": 27,
    "total_fragments_archivo": 37
  },
  {
    "archivo": "642330522.pdf",
    "fragmento_numero": 28,
    "total_fragments_archivo": 37
  },
  {
    "archivo": "642330522.pdf",
    "fragmento_numero": 29,
    "total_fragments_archivo": 37
  },
  {
    "archivo": "642330522.pdf",
    "fragmento_numero": 30,
    "total_fragments_archivo": 37
  },
  {
    "archivo": "642330522.pdf",
    "fragmento_numero": 31,
    "total_fragments_archivo": 37
  },
  {
    "archivo": "642330522.pdf",
    "fragmento_numero": 32,
    "total_fragments_archivo": 37
  },
  {
    "archivo": "642330522.pdf",
    "fragmento_numero": 33,
    "total_fragments_archivo": 37
  },
  {
    "archivo": "642330522.pdf",
    "fragmento_numero": 34,
    "total_fragments_archivo": 37
  },
  {
    "archivo": "642330522.pdf",
    "fragmento_numero": 35,
    "total_fragments_archivo": 37
  },
  {
    "archivo": "642330522.pdf",
    "fragmento_numero": 36,
    "total_fragments_archivo": 37
  },
  {
    "archivo": "642330522.pdf",
    "fragmento_numero": 37,
    "total_fragments_archivo": 37
  },
  {
    "archivo": "afma-mato+(1).pdf",
    "fragmento_numero": 1,
    "total_fragments_archivo": 20
  },
  {
    "archivo": "afma-mato+(1).pdf",
    "fragmento_numero": 2,
    "total_fragments_archivo": 20
  },
  {
    "archivo": "afma-mato+(1).pdf",
    "fragmento_numero": 3,
    "total_fragments_archivo": 20
  },
  {
    "archivo": "afma-mato+(1).pdf",
    "fragmento_numero": 4,
    "total_fragments_archivo": 20
  },
  {
    "archivo": "afma-mato+(1).pdf",
    "fragmento_numero": 5,
    "total_fragments_archivo": 20
  },
  {
    "archivo": "afma-mato+(1).pdf",
    "fragmento_numero": 6,
    "total_fragments_archivo": 20
  },
  {
    "archivo": "afma-mato+(1).pdf",
    "fragmento_numero": 7,
    "total_fragments_archivo": 20
  },
  {
    "archivo": "afma-mato+(1).pdf",
    "fragmento_numero": 8,
    "total_fragments_archivo": 20
  },
  {
    "archivo": "afma-mato+(1).pdf",
    "fragmento_numero": 9,
    "total_fragments_archivo": 20
  },
  {
    "archivo": "afma-mato+(1).pdf",
    "fragmento_numero": 10,
    "total_fragments_archivo": 20
  },
  {
    "archivo": "afma-mato+(1).pdf",
    "fragmento_numero": 11,
    "total_fragments_archivo": 20
  },
  {
    "archivo": "afma-mato+(1).pdf",
    "fragmento_numero": 12,
    "total_fragments_archivo": 20
  },
  {
    "archivo": "afma-mato+(1).pdf",
    "fragmento_numero": 13,
    "total_fragments_archivo": 20
  },
  {
    "archivo": "afma-mato+(1).pdf",
    "fragmento_numero": 14,
    "total_fragments_archivo": 20
  },
  {
    "archivo": "afma-mato+(1).pdf",
    "fragmento_numero": 15,
    "total_fragments_archivo": 20
  },
  {
    "archivo": "afma-mato+(1).pdf",
    "fragmento_numero": 16,
    "total_fragments_archivo": 20
  },
  {
    "archivo": "afma-mato+(1).pdf",
    "fragmento_numero": 17,
    "total_fragments_archivo": 20
  },
  {
    "archivo": "afma-mato+(1).pdf",
    "fragmento_numero": 18,
    "total_fragments_archivo": 20
  },
  {
    "archivo": "afma-mato+(1).pdf",
    "fragmento_numero": 19,
    "total_fragments_archivo": 20
  },
  {
    "archivo": "afma-mato+(1).pdf",
    "fragmento_numero": 20,
    "total_fragments_archivo": 20
  },
  {
    "archivo": "agriculture-13-00378-v3.pdf",
    "fragmento_numero": 1,
    "total_fragments_archivo": 21
  },
  {
    "archivo": "agriculture-13-00378-v3.pdf",
    "fragmento_numero": 2,
    "total_fragments_archivo": 21
  },
  {
    "archivo": "agriculture-13-00378-v3.pdf",
    "fragmento_numero": 3,
    "total_fragments_archivo": 21
  },
  {
    "archivo": "agriculture-13-00378-v3.pdf",
    "fragmento_numero": 4,
    "total_fragments_archivo": 21
  },
  {
    "archivo": "agriculture-13-00378-v3.pdf",
    "fragmento_numero": 5,
    "total_fragments_archivo": 21
  },
  {
    "archivo": "agriculture-13-00378-v3.pdf",
    "fragmento_numero": 6,
    "total_fragments_archivo": 21
  },
  {
    "archivo": "agriculture-13-00378-v3.pdf",
    "fragmento_numero": 7,
    "total_fragments_archivo": 21
  },
  {
    "archivo": "agriculture-13-00378-v3.pdf",
    "fragmento_numero": 8,
    "total_fragments_archivo": 21
  },
  {
    "archivo": "agriculture-13-00378-v3.pdf",
    "fragmento_numero": 9,
    "total_fragments_archivo": 21
  },
  {
    "archivo": "agriculture-13-00378-v3.pdf",
    "fragmento_numero": 10,
    "total_fragments_archivo": 21
  },
  {
    "archivo": "agriculture-13-00378-v3.pdf",
    "fragmento_numero": 11,
    "total_fragments_archivo": 21
  },
  {
    "archivo": "agriculture-13-00378-v3.pdf",
    "fragmento_numero": 12,
    "total_fragments_archivo": 21
  },
  {
    "archivo": "agriculture-13-00378-v3.pdf",
    "fragmento_numero": 13,
    "total_fragments_archivo": 21
  },
  {
    "archivo": "agriculture-13-00378-v3.pdf",
    "fragmento_numero": 14,
    "total_fragments_archivo": 21
  },
  {
    "archivo": "agriculture-13-00378-v3.pdf",
    "fragmento_numero": 15,
    "total_fragments_archivo": 21
  },
  {
    "archivo": "agriculture-13-00378-v3.pdf",
    "fragmento_numero": 16,
    "total_fragments_archivo": 21
  },
  {
    "archivo": "agriculture-13-00378-v3.pdf",
    "fragmento_numero": 17,
    "total_fragments_archivo": 21
  },
  {
    "archivo": "agriculture-13-00378-v3.pdf",
    "fragmento_numero": 18,
    "total_fragments_archivo": 21
  },
  {
    "archivo": "agriculture-13-00378-v3.pdf",
    "fragmento_numero": 19,
    "total_fragments_archivo": 21
  },
  {
    "archivo": "agriculture-13-00378-v3.pdf",
    "fragmento_numero": 20,
    "total_fragments_archivo": 21
  },
  {
    "archivo": "agriculture-13-00378-v3.pdf",
    "fragmento_numero": 21,
    "total_fragments_archivo": 21
  },
  {
    "archivo": "agriculture-14-00798.pdf",
    "fragmento_numero": 1,
    "total_fragments_archivo": 22
  },
  {
    "archivo": "agriculture-14-00798.pdf",
    "fragmento_numero": 2,
    "total_fragments_archivo": 22
  },
  {
    "archivo": "agriculture-14-00798.pdf",
    "fragmento_numero": 3,
    "total_fragments_archivo": 22
  },
  {
    "archivo": "agriculture-14-00798.pdf",
    "fragmento_numero": 4,
    "total_fragments_archivo": 22
  },
  {
    "archivo": "agriculture-14-00798.pdf",
    "fragmento_numero": 5,
    "total_fragments_archivo": 22
  },
  {
    "archivo": "agriculture-14-00798.pdf",
    "fragmento_numero": 6,
    "total_fragments_archivo": 22
  },
  {
    "archivo": "agriculture-14-00798.pdf",
    "fragmento_numero": 7,
    "total_fragments_archivo": 22
  },
  {
    "archivo": "agriculture-14-00798.pdf",
    "fragmento_numero": 8,
    "total_fragments_archivo": 22
  },
  {
    "archivo": "agriculture-14-00798.pdf",
    "fragmento_numero": 9,
    "total_fragments_archivo": 22
  },
  {
    "archivo": "agriculture-14-00798.pdf",
    "fragmento_numero": 10,
    "total_fragments_archivo": 22
  },
  {
    "archivo": "agriculture-14-00798.pdf",
    "fragmento_numero": 11,
    "total_fragments_archivo": 22
  },
  {
    "archivo": "agriculture-14-00798.pdf",
    "fragmento_numero": 12,
    "total_fragments_archivo": 22
  },
  {
    "archivo": "agriculture-14-00798.pdf",
    "fragmento_numero": 13,
    "total_fragments_archivo": 22
  },
  {
    "archivo": "agriculture-14-00798.pdf",
    "fragmento_numero": 14,
    "total_fragments_archivo": 22
  },
  {
    "archivo": "agriculture-14-00798.pdf",
    "fragmento_numero": 15,
    "total_fragments_archivo": 22
  },
  {
    "archivo": "agriculture-14-00798.pdf",
    "fragmento_numero": 16,
    "total_fragments_archivo": 22
  },
  {
    "archivo": "agriculture-14-00798.pdf",
    "fragmento_numero": 17,
    "total_fragments_archivo": 22
  },
  {
    "archivo": "agriculture-14-00798.pdf",
    "fragmento_numero": 18,
    "total_fragments_archivo": 22
  },
  {
    "archivo": "agriculture-14-00798.pdf",
    "fragmento_numero": 19,
    "total_fragments_archivo": 22
  },
  {
    "archivo": "agriculture-14-00798.pdf",
    "fragmento_numero": 20,
    "total_fragments_archivo": 22
  },
  {
    "archivo": "agriculture-14-00798.pdf",
    "fragmento_numero": 21,
    "total_fragments_archivo": 22
  },
  {
    "archivo": "agriculture-14-00798.pdf",
    "fragmento_numero": 22,
    "total_fragments_archivo": 22
  },
  {
    "archivo": "agriculture-tema.pdf",
    "fragmento_numero": 1,
    "total_fragments_archivo": 21
  },
  {
    "archivo": "agriculture-tema.pdf",
    "fragmento_numero": 2,
    "total_fragments_archivo": 21
  },
  {
    "archivo": "agriculture-tema.pdf",
    "fragmento_numero": 3,
    "total_fragments_archivo": 21
  },
  {
    "archivo": "agriculture-tema.pdf",
    "fragmento_numero": 4,
    "total_fragments_archivo": 21
  },
  {
    "archivo": "agriculture-tema.pdf",
    "fragmento_numero": 5,
    "total_fragments_archivo": 21
  },
  {
    "archivo": "agriculture-tema.pdf",
    "fragmento_numero": 6,
    "total_fragments_archivo": 21
  },
  {
    "archivo": "agriculture-tema.pdf",
    "fragmento_numero": 7,
    "total_fragments_archivo": 21
  },
  {
    "archivo": "agriculture-tema.pdf",
    "fragmento_numero": 8,
    "total_fragments_archivo": 21
  },
  {
    "archivo": "agriculture-tema.pdf",
    "fragmento_numero": 9,
    "total_fragments_archivo": 21
  },
  {
    "archivo": "agriculture-tema.pdf",
    "fragmento_numero": 10,
    "total_fragments_archivo": 21
  },
  {
    "archivo": "agriculture-tema.pdf",
    "fragmento_numero": 11,
    "total_fragments_archivo": 21
  },
  {
    "archivo": "agriculture-tema.pdf",
    "fragmento_numero": 12,
    "total_fragments_archivo": 21
  },
  {
    "archivo": "agriculture-tema.pdf",
    "fragmento_numero": 13,
    "total_fragments_archivo": 21
  },
  {
    "archivo": "agriculture-tema.pdf",
    "fragmento_numero": 14,
    "total_fragments_archivo": 21
  },
  {
    "archivo": "agriculture-tema.pdf",
    "fragmento_numero": 15,
    "total_fragments_archivo": 21
  },
  {
    "archivo": "agriculture-tema.pdf",
    "fragmento_numero": 16,
    "total_fragments_archivo": 21
  },
  {
    "archivo": "agriculture-tema.pdf",
    "fragmento_numero": 17,
    "total_fragments_archivo": 21
  },
  {
    "archivo": "agriculture-tema.pdf",
    "fragmento_numero": 18,
    "total_fragments_archivo": 21
  },
  {
    "archivo": "agriculture-tema.pdf",
    "fragmento_numero": 19,
    "total_fragments_archivo": 21
  },
  {
    "archivo": "agriculture-tema.pdf",
    "fragmento_numero": 20,
    "total_fragments_archivo": 21
  },
  {
    "archivo": "agriculture-tema.pdf",
    "fragmento_numero": 21,
    "total_fragments_archivo": 21
  },
  {
    "archivo": "de-nudman_v.pdf",
    "fragmento_numero": 1,
    "total_fragments_archivo": 165
  },
  {
    "archivo": "de-nudman_v.pdf",
    "fragmento_numero": 2,
    "total_fragments_archivo": 165
  },
  {
    "archivo": "de-nudman_v.pdf",
    "fragmento_numero": 3,
    "total_fragments_archivo": 165
  },
  {
    "archivo": "de-nudman_v.pdf",
    "fragmento_numero": 4,
    "total_fragments_archivo": 165
  },
  {
    "archivo": "de-nudman_v.pdf",
    "fragmento_numero": 5,
    "total_fragments_archivo": 165
  },
  {
    "archivo": "de-nudman_v.pdf",
    "fragmento_numero": 6,
    "total_fragments_archivo": 165
  },
  {
    "archivo": "de-nudman_v.pdf",
    "fragmento_numero": 7,
    "total_fragments_archivo": 165
  },
  {
    "archivo": "de-nudman_v.pdf",
    "fragmento_numero": 8,
    "total_fragments_archivo": 165
  },
  {
    "archivo": "de-nudman_v.pdf",
    "fragmento_numero": 9,
    "total_fragments_archivo": 165
  },
  {
    "archivo": "de-nudman_v.pdf",
    "fragmento_numero": 10,
    "total_fragments_archivo": 165
  },
  {
    "archivo": "de-nudman_v.pdf",
    "fragmento_numero": 11,
    "total_fragments_archivo": 165
  },
  {
    "archivo": "de-nudman_v.pdf",
    "fragmento_numero": 12,
    "total_fragments_archivo": 165
  },
  {
    "archivo": "de-nudman_v.pdf",
    "fragmento_numero": 13,
    "total_fragments_archivo": 165
  },
  {
    "archivo": "de-nudman_v.pdf",
    "fragmento_numero": 14,
    "total_fragments_archivo": 165
  },
  {
    "archivo": "de-nudman_v.pdf",
    "fragmento_numero": 15,
    "total_fragments_archivo": 165
  },
  {
    "archivo": "de-nudman_v.pdf",
    "fragmento_numero": 16,
    "total_fragments_archivo": 165
  },
  {
    "archivo": "de-nudman_v.pdf",
    "fragmento_numero": 17,
    "total_fragments_archivo": 165
  },
  {
    "archivo": "de-nudman_v.pdf",
    "fragmento_numero": 18,
    "total_fragments_archivo": 165
  },
  {
    "archivo": "de-nudman_v.pdf",
    "fragmento_numero": 19,
    "total_fragments_archivo": 165
  },
  {
    "archivo": "de-nudman_v.pdf",
    "fragmento_numero": 20,
    "total_fragments_archivo": 165
  },
  {
    "archivo": "de-nudman_v.pdf",
    "fragmento_numero": 21,
    "total_fragments_archivo": 165
  },
  {
    "archivo": "de-nudman_v.pdf",
    "fragmento_numero": 22,
    "total_fragments_archivo": 165
  },
  {
    "archivo": "de-nudman_v.pdf",
    "fragmento_numero": 23,
    "total_fragments_archivo": 165
  },
  {
    "archivo": "de-nudman_v.pdf",
    "fragmento_numero": 24,
    "total_fragments_archivo": 165
  },
  {
    "archivo": "de-nudman_v.pdf",
    "fragmento_numero": 25,
    "total_fragments_archivo": 165
  },
  {
    "archivo": "de-nudman_v.pdf",
    "fragmento_numero": 26,
    "total_fragments_archivo": 165
  },
  {
    "archivo": "de-nudman_v.pdf",
    "fragmento_numero": 27,
    "total_fragments_archivo": 165
  },
  {
    "archivo": "de-nudman_v.pdf",
    "fragmento_numero": 28,
    "total_fragments_archivo": 165
  },
  {
    "archivo": "de-nudman_v.pdf",
    "fragmento_numero": 29,
    "total_fragments_archivo": 165
  },
  {
    "archivo": "de-nudman_v.pdf",
    "fragmento_numero": 30,
    "total_fragments_archivo": 165
  },
  {
    "archivo": "de-nudman_v.pdf",
    "fragmento_numero": 31,
    "total_fragments_archivo": 165
  },
  {
    "archivo": "de-nudman_v.pdf",
    "fragmento_numero": 32,
    "total_fragments_archivo": 165
  },
  {
    "archivo": "de-nudman_v.pdf",
    "fragmento_numero": 33,
    "total_fragments_archivo": 165
  },
  {
    "archivo": "de-nudman_v.pdf",
    "fragmento_numero": 34,
    "total_fragments_archivo": 165
  },
  {
    "archivo": "de-nudman_v.pdf",
    "fragmento_numero": 35,
    "total_fragments_archivo": 165
  },
  {
    "archivo": "de-nudman_v.pdf",
    "fragmento_numero": 36,
    "total_fragments_archivo": 165
  },
  {
    "archivo": "de-nudman_v.pdf",
    "fragmento_numero": 37,
    "total_fragments_archivo": 165
  },
  {
    "archivo": "de-nudman_v.pdf",
    "fragmento_numero": 38,
    "total_fragments_archivo": 165
  },
  {
    "archivo": "de-nudman_v.pdf",
    "fragmento_numero": 39,
    "total_fragments_archivo": 165
  },
  {
    "archivo": "de-nudman_v.pdf",
    "fragmento_numero": 40,
    "total_fragments_archivo": 165
  },
  {
    "archivo": "de-nudman_v.pdf",
    "fragmento_numero": 41,
    "total_fragments_archivo": 165
  },
  {
    "archivo": "de-nudman_v.pdf",
    "fragmento_numero": 42,
    "total_fragments_archivo": 165
  },
  {
    "archivo": "de-nudman_v.pdf",
    "fragmento_numero": 43,
    "total_fragments_archivo": 165
  },
  {
    "archivo": "de-nudman_v.pdf",
    "fragmento_numero": 44,
    "total_fragments_archivo": 165
  },
  {
    "archivo": "de-nudman_v.pdf",
    "fragmento_numero": 45,
    "total_fragments_archivo": 165
  },
  {
    "archivo": "de-nudman_v.pdf",
    "fragmento_numero": 46,
    "total_fragments_archivo": 165
  },
  {
    "archivo": "de-nudman_v.pdf",
    "fragmento_numero": 47,
    "total_fragments_archivo": 165
  },
  {
    "archivo": "de-nudman_v.pdf",
    "fragmento_numero": 48,
    "total_fragments_archivo": 165
  },
  {
    "archivo": "de-nudman_v.pdf",
    "fragmento_numero": 49,
    "total_fragments_archivo": 165
  },
  {
    "archivo": "de-nudman_v.pdf",
    "fragmento_numero": 50,
    "total_fragments_archivo": 165
  },
  {
    "archivo": "de-nudman_v.pdf",
    "fragmento_numero": 51,
    "total_fragments_archivo": 165
  },
  {
    "archivo": "de-nudman_v.pdf",
    "fragmento_numero": 52,
    "total_fragments_archivo": 165
  },
  {
    "archivo": "de-nudman_v.pdf",
    "fragmento_numero": 53,
    "total_fragments_archivo": 165
  },
  {
    "archivo": "de-nudman_v.pdf",
    "fragmento_numero": 54,
    "total_fragments_archivo": 165
  },
  {
    "archivo": "de-nudman_v.pdf",
    "fragmento_numero": 55,
    "total_fragments_archivo": 165
  },
  {
    "archivo": "de-nudman_v.pdf",
    "fragmento_numero": 56,
    "total_fragments_archivo": 165
  },
  {
    "archivo": "de-nudman_v.pdf",
    "fragmento_numero": 57,
    "total_fragments_archivo": 165
  },
  {
    "archivo": "de-nudman_v.pdf",
    "fragmento_numero": 58,
    "total_fragments_archivo": 165
  },
  {
    "archivo": "de-nudman_v.pdf",
    "fragmento_numero": 59,
    "total_fragments_archivo": 165
  },
  {
    "archivo": "de-nudman_v.pdf",
    "fragmento_numero": 60,
    "total_fragments_archivo": 165
  },
  {
    "archivo": "de-nudman_v.pdf",
    "fragmento_numero": 61,
    "total_fragments_archivo": 165
  },
  {
    "archivo": "de-nudman_v.pdf",
    "fragmento_numero": 62,
    "total_fragments_archivo": 165
  },
  {
    "archivo": "de-nudman_v.pdf",
    "fragmento_numero": 63,
    "total_fragments_archivo": 165
  },
  {
    "archivo": "de-nudman_v.pdf",
    "fragmento_numero": 64,
    "total_fragments_archivo": 165
  },
  {
    "archivo": "de-nudman_v.pdf",
    "fragmento_numero": 65,
    "total_fragments_archivo": 165
  },
  {
    "archivo": "de-nudman_v.pdf",
    "fragmento_numero": 66,
    "total_fragments_archivo": 165
  },
  {
    "archivo": "de-nudman_v.pdf",
    "fragmento_numero": 67,
    "total_fragments_archivo": 165
  },
  {
    "archivo": "de-nudman_v.pdf",
    "fragmento_numero": 68,
    "total_fragments_archivo": 165
  },
  {
    "archivo": "de-nudman_v.pdf",
    "fragmento_numero": 69,
    "total_fragments_archivo": 165
  },
  {
    "archivo": "de-nudman_v.pdf",
    "fragmento_numero": 70,
    "total_fragments_archivo": 165
  },
  {
    "archivo": "de-nudman_v.pdf",
    "fragmento_numero": 71,
    "total_fragments_archivo": 165
  },
  {
    "archivo": "de-nudman_v.pdf",
    "fragmento_numero": 72,
    "total_fragments_archivo": 165
  },
  {
    "archivo": "de-nudman_v.pdf",
    "fragmento_numero": 73,
    "total_fragments_archivo": 165
  },
  {
    "archivo": "de-nudman_v.pdf",
    "fragmento_numero": 74,
    "total_fragments_archivo": 165
  },
  {
    "archivo": "de-nudman_v.pdf",
    "fragmento_numero": 75,
    "total_fragments_archivo": 165
  },
  {
    "archivo": "de-nudman_v.pdf",
    "fragmento_numero": 76,
    "total_fragments_archivo": 165
  },
  {
    "archivo": "de-nudman_v.pdf",
    "fragmento_numero": 77,
    "total_fragments_archivo": 165
  },
  {
    "archivo": "de-nudman_v.pdf",
    "fragmento_numero": 78,
    "total_fragments_archivo": 165
  },
  {
    "archivo": "de-nudman_v.pdf",
    "fragmento_numero": 79,
    "total_fragments_archivo": 165
  },
  {
    "archivo": "de-nudman_v.pdf",
    "fragmento_numero": 80,
    "total_fragments_archivo": 165
  },
  {
    "archivo": "de-nudman_v.pdf",
    "fragmento_numero": 81,
    "total_fragments_archivo": 165
  },
  {
    "archivo": "de-nudman_v.pdf",
    "fragmento_numero": 82,
    "total_fragments_archivo": 165
  },
  {
    "archivo": "de-nudman_v.pdf",
    "fragmento_numero": 83,
    "total_fragments_archivo": 165
  },
  {
    "archivo": "de-nudman_v.pdf",
    "fragmento_numero": 84,
    "total_fragments_archivo": 165
  },
  {
    "archivo": "de-nudman_v.pdf",
    "fragmento_numero": 85,
    "total_fragments_archivo": 165
  },
  {
    "archivo": "de-nudman_v.pdf",
    "fragmento_numero": 86,
    "total_fragments_archivo": 165
  },
  {
    "archivo": "de-nudman_v.pdf",
    "fragmento_numero": 87,
    "total_fragments_archivo": 165
  },
  {
    "archivo": "de-nudman_v.pdf",
    "fragmento_numero": 88,
    "total_fragments_archivo": 165
  },
  {
    "archivo": "de-nudman_v.pdf",
    "fragmento_numero": 89,
    "total_fragments_archivo": 165
  },
  {
    "archivo": "de-nudman_v.pdf",
    "fragmento_numero": 90,
    "total_fragments_archivo": 165
  },
  {
    "archivo": "de-nudman_v.pdf",
    "fragmento_numero": 91,
    "total_fragments_archivo": 165
  },
  {
    "archivo": "de-nudman_v.pdf",
    "fragmento_numero": 92,
    "total_fragments_archivo": 165
  },
  {
    "archivo": "de-nudman_v.pdf",
    "fragmento_numero": 93,
    "total_fragments_archivo": 165
  },
  {
    "archivo": "de-nudman_v.pdf",
    "fragmento_numero": 94,
    "total_fragments_archivo": 165
  },
  {
    "archivo": "de-nudman_v.pdf",
    "fragmento_numero": 95,
    "total_fragments_archivo": 165
  },
  {
    "archivo": "de-nudman_v.pdf",
    "fragmento_numero": 96,
    "total_fragments_archivo": 165
  },
  {
    "archivo": "de-nudman_v.pdf",
    "fragmento_numero": 97,
    "total_fragments_archivo": 165
  },
  {
    "archivo": "de-nudman_v.pdf",
    "fragmento_numero": 98,
    "total_fragments_archivo": 165
  },
  {
    "archivo": "de-nudman_v.pdf",
    "fragmento_numero": 99,
    "total_fragments_archivo": 165
  },
  {
    "archivo": "de-nudman_v.pdf",
    "fragmento_numero": 100,
    "total_fragments_archivo": 165
  },
  {
    "archivo": "de-nudman_v.pdf",
    "fragmento_numero": 101,
    "total_fragments_archivo": 165
  },
  {
    "archivo": "de-nudman_v.pdf",
    "fragmento_numero": 102,
    "total_fragments_archivo": 165
  },
  {
    "archivo": "de-nudman_v.pdf",
    "fragmento_numero": 103,
    "total_fragments_archivo": 165
  },
  {
    "archivo": "de-nudman_v.pdf",
    "fragmento_numero": 104,
    "total_fragments_archivo": 165
  },
  {
    "archivo": "de-nudman_v.pdf",
    "fragmento_numero": 105,
    "total_fragments_archivo": 165
  },
  {
    "archivo": "de-nudman_v.pdf",
    "fragmento_numero": 106,
    "total_fragments_archivo": 165
  },
  {
    "archivo": "de-nudman_v.pdf",
    "fragmento_numero": 107,
    "total_fragments_archivo": 165
  },
  {
    "archivo": "de-nudman_v.pdf",
    "fragmento_numero": 108,
    "total_fragments_archivo": 165
  },
  {
    "archivo": "de-nudman_v.pdf",
    "fragmento_numero": 109,
    "total_fragments_archivo": 165
  },
  {
    "archivo": "de-nudman_v.pdf",
    "fragmento_numero": 110,
    "total_fragments_archivo": 165
  },
  {
    "archivo": "de-nudman_v.pdf",
    "fragmento_numero": 111,
    "total_fragments_archivo": 165
  },
  {
    "archivo": "de-nudman_v.pdf",
    "fragmento_numero": 112,
    "total_fragments_archivo": 165
  },
  {
    "archivo": "de-nudman_v.pdf",
    "fragmento_numero": 113,
    "total_fragments_archivo": 165
  },
  {
    "archivo": "de-nudman_v.pdf",
    "fragmento_numero": 114,
    "total_fragments_archivo": 165
  },
  {
    "archivo": "de-nudman_v.pdf",
    "fragmento_numero": 115,
    "total_fragments_archivo": 165
  },
  {
    "archivo": "de-nudman_v.pdf",
    "fragmento_numero": 116,
    "total_fragments_archivo": 165
  },
  {
    "archivo": "de-nudman_v.pdf",
    "fragmento_numero": 117,
    "total_fragments_archivo": 165
  },
  {
    "archivo": "de-nudman_v.pdf",
    "fragmento_numero": 118,
    "total_fragments_archivo": 165
  },
  {
    "archivo": "de-nudman_v.pdf",
    "fragmento_numero": 119,
    "total_fragments_archivo": 165
  },
  {
    "archivo": "de-nudman_v.pdf",
    "fragmento_numero": 120,
    "total_fragments_archivo": 165
  },
  {
    "archivo": "de-nudman_v.pdf",
    "fragmento_numero": 121,
    "total_fragments_archivo": 165
  },
  {
    "archivo": "de-nudman_v.pdf",
    "fragmento_numero": 122,
    "total_fragments_archivo": 165
  },
  {
    "archivo": "de-nudman_v.pdf",
    "fragmento_numero": 123,
    "total_fragments_archivo": 165
  },
  {
    "archivo": "de-nudman_v.pdf",
    "fragmento_numero": 124,
    "total_fragments_archivo": 165
  },
  {
    "archivo": "de-nudman_v.pdf",
    "fragmento_numero": 125,
    "total_fragments_archivo": 165
  },
  {
    "archivo": "de-nudman_v.pdf",
    "fragmento_numero": 126,
    "total_fragments_archivo": 165
  },
  {
    "archivo": "de-nudman_v.pdf",
    "fragmento_numero": 127,
    "total_fragments_archivo": 165
  },
  {
    "archivo": "de-nudman_v.pdf",
    "fragmento_numero": 128,
    "total_fragments_archivo": 165
  },
  {
    "archivo": "de-nudman_v.pdf",
    "fragmento_numero": 129,
    "total_fragments_archivo": 165
  },
  {
    "archivo": "de-nudman_v.pdf",
    "fragmento_numero": 130,
    "total_fragments_archivo": 165
  },
  {
    "archivo": "de-nudman_v.pdf",
    "fragmento_numero": 131,
    "total_fragments_archivo": 165
  },
  {
    "archivo": "de-nudman_v.pdf",
    "fragmento_numero": 132,
    "total_fragments_archivo": 165
  },
  {
    "archivo": "de-nudman_v.pdf",
    "fragmento_numero": 133,
    "total_fragments_archivo": 165
  },
  {
    "archivo": "de-nudman_v.pdf",
    "fragmento_numero": 134,
    "total_fragments_archivo": 165
  },
  {
    "archivo": "de-nudman_v.pdf",
    "fragmento_numero": 135,
    "total_fragments_archivo": 165
  },
  {
    "archivo": "de-nudman_v.pdf",
    "fragmento_numero": 136,
    "total_fragments_archivo": 165
  },
  {
    "archivo": "de-nudman_v.pdf",
    "fragmento_numero": 137,
    "total_fragments_archivo": 165
  },
  {
    "archivo": "de-nudman_v.pdf",
    "fragmento_numero": 138,
    "total_fragments_archivo": 165
  },
  {
    "archivo": "de-nudman_v.pdf",
    "fragmento_numero": 139,
    "total_fragments_archivo": 165
  },
  {
    "archivo": "de-nudman_v.pdf",
    "fragmento_numero": 140,
    "total_fragments_archivo": 165
  },
  {
    "archivo": "de-nudman_v.pdf",
    "fragmento_numero": 141,
    "total_fragments_archivo": 165
  },
  {
    "archivo": "de-nudman_v.pdf",
    "fragmento_numero": 142,
    "total_fragments_archivo": 165
  },
  {
    "archivo": "de-nudman_v.pdf",
    "fragmento_numero": 143,
    "total_fragments_archivo": 165
  },
  {
    "archivo": "de-nudman_v.pdf",
    "fragmento_numero": 144,
    "total_fragments_archivo": 165
  },
  {
    "archivo": "de-nudman_v.pdf",
    "fragmento_numero": 145,
    "total_fragments_archivo": 165
  },
  {
    "archivo": "de-nudman_v.pdf",
    "fragmento_numero": 146,
    "total_fragments_archivo": 165
  },
  {
    "archivo": "de-nudman_v.pdf",
    "fragmento_numero": 147,
    "total_fragments_archivo": 165
  },
  {
    "archivo": "de-nudman_v.pdf",
    "fragmento_numero": 148,
    "total_fragments_archivo": 165
  },
  {
    "archivo": "de-nudman_v.pdf",
    "fragmento_numero": 149,
    "total_fragments_archivo": 165
  },
  {
    "archivo": "de-nudman_v.pdf",
    "fragmento_numero": 150,
    "total_fragments_archivo": 165
  },
  {
    "archivo": "de-nudman_v.pdf",
    "fragmento_numero": 151,
    "total_fragments_archivo": 165
  },
  {
    "archivo": "de-nudman_v.pdf",
    "fragmento_numero": 152,
    "total_fragments_archivo": 165
  },
  {
    "archivo": "de-nudman_v.pdf",
    "fragmento_numero": 153,
    "total_fragments_archivo": 165
  },
  {
    "archivo": "de-nudman_v.pdf",
    "fragmento_numero": 154,
    "total_fragments_archivo": 165
  },
  {
    "archivo": "de-nudman_v.pdf",
    "fragmento_numero": 155,
    "total_fragments_archivo": 165
  },
  {
    "archivo": "de-nudman_v.pdf",
    "fragmento_numero": 156,
    "total_fragments_archivo": 165
  },
  {
    "archivo": "de-nudman_v.pdf",
    "fragmento_numero": 157,
    "total_fragments_archivo": 165
  },
  {
    "archivo": "de-nudman_v.pdf",
    "fragmento_numero": 158,
    "total_fragments_archivo": 165
  },
  {
    "archivo": "de-nudman_v.pdf",
    "fragmento_numero": 159,
    "total_fragments_archivo": 165
  },
  {
    "archivo": "de-nudman_v.pdf",
    "fragmento_numero": 160,
    "total_fragments_archivo": 165
  },
  {
    "archivo": "de-nudman_v.pdf",
    "fragmento_numero": 161,
    "total_fragments_archivo": 165
  },
  {
    "archivo": "de-nudman_v.pdf",
    "fragmento_numero": 162,
    "total_fragments_archivo": 165
  },
  {
    "archivo": "de-nudman_v.pdf",
    "fragmento_numero": 163,
    "total_fragments_archivo": 165
  },
  {
    "archivo": "de-nudman_v.pdf",
    "fragmento_numero": 164,
    "total_fragments_archivo": 165
  },
  {
    "archivo": "de-nudman_v.pdf",
    "fragmento_numero": 165,
    "total_fragments_archivo": 165
  },
  {
    "archivo": "document.pdf",
    "fragmento_numero": 1,
    "total_fragments_archivo": 50
  },
  {
    "archivo": "document.pdf",
    "fragmento_numero": 2,
    "total_fragments_archivo": 50
  },
  {
    "archivo": "document.pdf",
    "fragmento_numero": 3,
    "total_fragments_archivo": 50
  },
  {
    "archivo": "document.pdf",
    "fragmento_numero": 4,
    "total_fragments_archivo": 50
  },
  {
    "archivo": "document.pdf",
    "fragmento_numero": 5,
    "total_fragments_archivo": 50
  },
  {
    "archivo": "document.pdf",
    "fragmento_numero": 6,
    "total_fragments_archivo": 50
  },
  {
    "archivo": "document.pdf",
    "fragmento_numero": 7,
    "total_fragments_archivo": 50
  },
  {
    "archivo": "document.pdf",
    "fragmento_numero": 8,
    "total_fragments_archivo": 50
  },
  {
    "archivo": "document.pdf",
    "fragmento_numero": 9,
    "total_fragments_archivo": 50
  },
  {
    "archivo": "document.pdf",
    "fragmento_numero": 10,
    "total_fragments_archivo": 50
  },
  {
    "archivo": "document.pdf",
    "fragmento_numero": 11,
    "total_fragments_archivo": 50
  },
  {
    "archivo": "document.pdf",
    "fragmento_numero": 12,
    "total_fragments_archivo": 50
  },
  {
    "archivo": "document.pdf",
    "fragmento_numero": 13,
    "total_fragments_archivo": 50
  },
  {
    "archivo": "document.pdf",
    "fragmento_numero": 14,
    "total_fragments_archivo": 50
  },
  {
    "archivo": "document.pdf",
    "fragmento_numero": 15,
    "total_fragments_archivo": 50
  },
  {
    "archivo": "document.pdf",
    "fragmento_numero": 16,
    "total_fragments_archivo": 50
  },
  {
    "archivo": "document.pdf",
    "fragmento_numero": 17,
    "total_fragments_archivo": 50
  },
  {
    "archivo": "document.pdf",
    "fragmento_numero": 18,
    "total_fragments_archivo": 50
  },
  {
    "archivo": "document.pdf",
    "fragmento_numero": 19,
    "total_fragments_archivo": 50
  },
  {
    "archivo": "document.pdf",
    "fragmento_numero": 20,
    "total_fragments_archivo": 50
  },
  {
    "archivo": "document.pdf",
    "fragmento_numero": 21,
    "total_fragments_archivo": 50
  },
  {
    "archivo": "document.pdf",
    "fragmento_numero": 22,
    "total_fragments_archivo": 50
  },
  {
    "archivo": "document.pdf",
    "fragmento_numero": 23,
    "total_fragments_archivo": 50
  },
  {
    "archivo": "document.pdf",
    "fragmento_numero": 24,
    "total_fragments_archivo": 50
  },
  {
    "archivo": "document.pdf",
    "fragmento_numero": 25,
    "total_fragments_archivo": 50
  },
  {
    "archivo": "document.pdf",
    "fragmento_numero": 26,
    "total_fragments_archivo": 50
  },
  {
    "archivo": "document.pdf",
    "fragmento_numero": 27,
    "total_fragments_archivo": 50
  },
  {
    "archivo": "document.pdf",
    "fragmento_numero": 28,
    "total_fragments_archivo": 50
  },
  {
    "archivo": "document.pdf",
    "fragmento_numero": 29,
    "total_fragments_archivo": 50
  },
  {
    "archivo": "document.pdf",
    "fragmento_numero": 30,
    "total_fragments_archivo": 50
  },
  {
    "archivo": "document.pdf",
    "fragmento_numero": 31,
    "total_fragments_archivo": 50
  },
  {
    "archivo": "document.pdf",
    "fragmento_numero": 32,
    "total_fragments_archivo": 50
  },
  {
    "archivo": "document.pdf",
    "fragmento_numero": 33,
    "total_fragments_archivo": 50
  },
  {
    "archivo": "document.pdf",
    "fragmento_numero": 34,
    "total_fragments_archivo": 50
  },
  {
    "archivo": "document.pdf",
    "fragmento_numero": 35,
    "total_fragments_archivo": 50
  },
  {
    "archivo": "document.pdf",
    "fragmento_numero": 36,
    "total_fragments_archivo": 50
  },
  {
    "archivo": "document.pdf",
    "fragmento_numero": 37,
    "total_fragments_archivo": 50
  },
  {
    "archivo": "document.pdf",
    "fragmento_numero": 38,
    "total_fragments_archivo": 50
  },
  {
    "archivo": "document.pdf",
    "fragmento_numero": 39,
    "total_fragments_archivo": 50
  },
  {
    "archivo": "document.pdf",
    "fragmento_numero": 40,
    "total_fragments_archivo": 50
  },
  {
    "archivo": "document.pdf",
    "fragmento_numero": 41,
    "total_fragments_archivo": 50
  },
  {
    "archivo": "document.pdf",
    "fragmento_numero": 42,
    "total_fragments_archivo": 50
  },
  {
    "archivo": "document.pdf",
    "fragmento_numero": 43,
    "total_fragments_archivo": 50
  },
  {
    "archivo": "document.pdf",
    "fragmento_numero": 44,
    "total_fragments_archivo": 50
  },
  {
    "archivo": "document.pdf",
    "fragmento_numero": 45,
    "total_fragments_archivo": 50
  },
  {
    "archivo": "document.pdf",
    "fragmento_numero": 46,
    "total_fragments_archivo": 50
  },
  {
    "archivo": "document.pdf",
    "fragmento_numero": 47,
    "total_fragments_archivo": 50
  },
  {
    "archivo": "document.pdf",
    "fragmento_numero": 48,
    "total_fragments_archivo": 50
  },
  {
    "archivo": "document.pdf",
    "fragmento_numero": 49,
    "total_fragments_archivo": 50
  },
  {
    "archivo": "document.pdf",
    "fragmento_numero": 50,
    "total_fragments_archivo": 50
  },
  {
    "archivo": "Productos típicos y Sello de Origen (Región de O’Higgins, Chile).pdf",
    "fragmento_numero": 1,
    "total_fragments_archivo": 20
  },
  {
    "archivo": "Productos típicos y Sello de Origen (Región de O’Higgins, Chile).pdf",
    "fragmento_numero": 2,
    "total_fragments_archivo": 20
  },
  {
    "archivo": "Productos típicos y Sello de Origen (Región de O’Higgins, Chile).pdf",
    "fragmento_numero": 3,
    "total_fragments_archivo": 20
  },
  {
    "archivo": "Productos típicos y Sello de Origen (Región de O’Higgins, Chile).pdf",
    "fragmento_numero": 4,
    "total_fragments_archivo": 20
  },
  {
    "archivo": "Productos típicos y Sello de Origen (Región de O’Higgins, Chile).pdf",
    "fragmento_numero": 5,
    "total_fragments_archivo": 20
  },
  {
    "archivo": "Productos típicos y Sello de Origen (Región de O’Higgins, Chile).pdf",
    "fragmento_numero": 6,
    "total_fragments_archivo": 20
  },
  {
    "archivo": "Productos típicos y Sello de Origen (Región de O’Higgins, Chile).pdf",
    "fragmento_numero": 7,
    "total_fragments_archivo": 20
  },
  {
    "archivo": "Productos típicos y Sello de Origen (Región de O’Higgins, Chile).pdf",
    "fragmento_numero": 8,
    "total_fragments_archivo": 20
  },
  {
    "archivo": "Productos típicos y Sello de Origen (Región de O’Higgins, Chile).pdf",
    "fragmento_numero": 9,
    "total_fragments_archivo": 20
  },
  {
    "archivo": "Productos típicos y Sello de Origen (Región de O’Higgins, Chile).pdf",
    "fragmento_numero": 10,
    "total_fragments_archivo": 20
  },
  {
    "archivo": "Productos típicos y Sello de Origen (Región de O’Higgins, Chile).pdf",
    "fragmento_numero": 11,
    "total_fragments_archivo": 20
  },
  {
    "archivo": "Productos típicos y Sello de Origen (Región de O’Higgins, Chile).pdf",
    "fragmento_numero": 12,
    "total_fragments_archivo": 20
  },
  {
    "archivo": "Productos típicos y Sello de Origen (Región de O’Higgins, Chile).pdf",
    "fragmento_numero": 13,
    "total_fragments_archivo": 20
  },
  {
    "archivo": "Productos típicos y Sello de Origen (Región de O’Higgins, Chile).pdf",
    "fragmento_numero": 14,
    "total_fragments_archivo": 20
  },
  {
    "archivo": "Productos típicos y Sello de Origen (Región de O’Higgins, Chile).pdf",
    "fragmento_numero": 15,
    "total_fragments_archivo": 20
  },
  {
    "archivo": "Productos típicos y Sello de Origen (Región de O’Higgins, Chile).pdf",
    "fragmento_numero": 16,
    "total_fragments_archivo": 20
  },
  {
    "archivo": "Productos típicos y Sello de Origen (Región de O’Higgins, Chile).pdf",
    "fragmento_numero": 17,
    "total_fragments_archivo": 20
  },
  {
    "archivo": "Productos típicos y Sello de Origen (Región de O’Higgins, Chile).pdf",
    "fragmento_numero": 18,
    "total_fragments_archivo": 20
  },
  {
    "archivo": "Productos típicos y Sello de Origen (Región de O’Higgins, Chile).pdf",
    "fragmento_numero": 19,
    "total_fragments_archivo": 20
  },
  {
    "archivo": "Productos típicos y Sello de Origen (Región de O’Higgins, Chile).pdf",
    "fragmento_numero": 20,
    "total_fragments_archivo": 20
  },
  {
    "archivo": "Que_factores_deben_acompanar_a_una_denominacion_de_origen_para_que_su_potencial_efecto_de_fomento_al_turismo_sea_eficaz.pdf",
    "fragmento_numero": 1,
    "total_fragments_archivo": 37
  },
  {
    "archivo": "Que_factores_deben_acompanar_a_una_denominacion_de_origen_para_que_su_potencial_efecto_de_fomento_al_turismo_sea_eficaz.pdf",
    "fragmento_numero": 2,
    "total_fragments_archivo": 37
  },
  {
    "archivo": "Que_factores_deben_acompanar_a_una_denominacion_de_origen_para_que_su_potencial_efecto_de_fomento_al_turismo_sea_eficaz.pdf",
    "fragmento_numero": 3,
    "total_fragments_archivo": 37
  },
  {
    "archivo": "Que_factores_deben_acompanar_a_una_denominacion_de_origen_para_que_su_potencial_efecto_de_fomento_al_turismo_sea_eficaz.pdf",
    "fragmento_numero": 4,
    "total_fragments_archivo": 37
  },
  {
    "archivo": "Que_factores_deben_acompanar_a_una_denominacion_de_origen_para_que_su_potencial_efecto_de_fomento_al_turismo_sea_eficaz.pdf",
    "fragmento_numero": 5,
    "total_fragments_archivo": 37
  },
  {
    "archivo": "Que_factores_deben_acompanar_a_una_denominacion_de_origen_para_que_su_potencial_efecto_de_fomento_al_turismo_sea_eficaz.pdf",
    "fragmento_numero": 6,
    "total_fragments_archivo": 37
  },
  {
    "archivo": "Que_factores_deben_acompanar_a_una_denominacion_de_origen_para_que_su_potencial_efecto_de_fomento_al_turismo_sea_eficaz.pdf",
    "fragmento_numero": 7,
    "total_fragments_archivo": 37
  },
  {
    "archivo": "Que_factores_deben_acompanar_a_una_denominacion_de_origen_para_que_su_potencial_efecto_de_fomento_al_turismo_sea_eficaz.pdf",
    "fragmento_numero": 8,
    "total_fragments_archivo": 37
  },
  {
    "archivo": "Que_factores_deben_acompanar_a_una_denominacion_de_origen_para_que_su_potencial_efecto_de_fomento_al_turismo_sea_eficaz.pdf",
    "fragmento_numero": 9,
    "total_fragments_archivo": 37
  },
  {
    "archivo": "Que_factores_deben_acompanar_a_una_denominacion_de_origen_para_que_su_potencial_efecto_de_fomento_al_turismo_sea_eficaz.pdf",
    "fragmento_numero": 10,
    "total_fragments_archivo": 37
  },
  {
    "archivo": "Que_factores_deben_acompanar_a_una_denominacion_de_origen_para_que_su_potencial_efecto_de_fomento_al_turismo_sea_eficaz.pdf",
    "fragmento_numero": 11,
    "total_fragments_archivo": 37
  },
  {
    "archivo": "Que_factores_deben_acompanar_a_una_denominacion_de_origen_para_que_su_potencial_efecto_de_fomento_al_turismo_sea_eficaz.pdf",
    "fragmento_numero": 12,
    "total_fragments_archivo": 37
  },
  {
    "archivo": "Que_factores_deben_acompanar_a_una_denominacion_de_origen_para_que_su_potencial_efecto_de_fomento_al_turismo_sea_eficaz.pdf",
    "fragmento_numero": 13,
    "total_fragments_archivo": 37
  },
  {
    "archivo": "Que_factores_deben_acompanar_a_una_denominacion_de_origen_para_que_su_potencial_efecto_de_fomento_al_turismo_sea_eficaz.pdf",
    "fragmento_numero": 14,
    "total_fragments_archivo": 37
  },
  {
    "archivo": "Que_factores_deben_acompanar_a_una_denominacion_de_origen_para_que_su_potencial_efecto_de_fomento_al_turismo_sea_eficaz.pdf",
    "fragmento_numero": 15,
    "total_fragments_archivo": 37
  },
  {
    "archivo": "Que_factores_deben_acompanar_a_una_denominacion_de_origen_para_que_su_potencial_efecto_de_fomento_al_turismo_sea_eficaz.pdf",
    "fragmento_numero": 16,
    "total_fragments_archivo": 37
  },
  {
    "archivo": "Que_factores_deben_acompanar_a_una_denominacion_de_origen_para_que_su_potencial_efecto_de_fomento_al_turismo_sea_eficaz.pdf",
    "fragmento_numero": 17,
    "total_fragments_archivo": 37
  },
  {
    "archivo": "Que_factores_deben_acompanar_a_una_denominacion_de_origen_para_que_su_potencial_efecto_de_fomento_al_turismo_sea_eficaz.pdf",
    "fragmento_numero": 18,
    "total_fragments_archivo": 37
  },
  {
    "archivo": "Que_factores_deben_acompanar_a_una_denominacion_de_origen_para_que_su_potencial_efecto_de_fomento_al_turismo_sea_eficaz.pdf",
    "fragmento_numero": 19,
    "total_fragments_archivo": 37
  },
  {
    "archivo": "Que_factores_deben_acompanar_a_una_denominacion_de_origen_para_que_su_potencial_efecto_de_fomento_al_turismo_sea_eficaz.pdf",
    "fragmento_numero": 20,
    "total_fragments_archivo": 37
  },
  {
    "archivo": "Que_factores_deben_acompanar_a_una_denominacion_de_origen_para_que_su_potencial_efecto_de_fomento_al_turismo_sea_eficaz.pdf",
    "fragmento_numero": 21,
    "total_fragments_archivo": 37
  },
  {
    "archivo": "Que_factores_deben_acompanar_a_una_denominacion_de_origen_para_que_su_potencial_efecto_de_fomento_al_turismo_sea_eficaz.pdf",
    "fragmento_numero": 22,
    "total_fragments_archivo": 37
  },
  {
    "archivo": "Que_factores_deben_acompanar_a_una_denominacion_de_origen_para_que_su_potencial_efecto_de_fomento_al_turismo_sea_eficaz.pdf",
    "fragmento_numero": 23,
    "total_fragments_archivo": 37
  },
  {
    "archivo": "Que_factores_deben_acompanar_a_una_denominacion_de_origen_para_que_su_potencial_efecto_de_fomento_al_turismo_sea_eficaz.pdf",
    "fragmento_numero": 24,
    "total_fragments_archivo": 37
  },
  {
    "archivo": "Que_factores_deben_acompanar_a_una_denominacion_de_origen_para_que_su_potencial_efecto_de_fomento_al_turismo_sea_eficaz.pdf",
    "fragmento_numero": 25,
    "total_fragments_archivo": 37
  },
  {
    "archivo": "Que_factores_deben_acompanar_a_una_denominacion_de_origen_para_que_su_potencial_efecto_de_fomento_al_turismo_sea_eficaz.pdf",
    "fragmento_numero": 26,
    "total_fragments_archivo": 37
  },
  {
    "archivo": "Que_factores_deben_acompanar_a_una_denominacion_de_origen_para_que_su_potencial_efecto_de_fomento_al_turismo_sea_eficaz.pdf",
    "fragmento_numero": 27,
    "total_fragments_archivo": 37
  },
  {
    "archivo": "Que_factores_deben_acompanar_a_una_denominacion_de_origen_para_que_su_potencial_efecto_de_fomento_al_turismo_sea_eficaz.pdf",
    "fragmento_numero": 28,
    "total_fragments_archivo": 37
  },
  {
    "archivo": "Que_factores_deben_acompanar_a_una_denominacion_de_origen_para_que_su_potencial_efecto_de_fomento_al_turismo_sea_eficaz.pdf",
    "fragmento_numero": 29,
    "total_fragments_archivo": 37
  },
  {
    "archivo": "Que_factores_deben_acompanar_a_una_denominacion_de_origen_para_que_su_potencial_efecto_de_fomento_al_turismo_sea_eficaz.pdf",
    "fragmento_numero": 30,
    "total_fragments_archivo": 37
  },
  {
    "archivo": "Que_factores_deben_acompanar_a_una_denominacion_de_origen_para_que_su_potencial_efecto_de_fomento_al_turismo_sea_eficaz.pdf",
    "fragmento_numero": 31,
    "total_fragments_archivo": 37
  },
  {
    "archivo": "Que_factores_deben_acompanar_a_una_denominacion_de_origen_para_que_su_potencial_efecto_de_fomento_al_turismo_sea_eficaz.pdf",
    "fragmento_numero": 32,
    "total_fragments_archivo": 37
  },
  {
    "archivo": "Que_factores_deben_acompanar_a_una_denominacion_de_origen_para_que_su_potencial_efecto_de_fomento_al_turismo_sea_eficaz.pdf",
    "fragmento_numero": 33,
    "total_fragments_archivo": 37
  },
  {
    "archivo": "Que_factores_deben_acompanar_a_una_denominacion_de_origen_para_que_su_potencial_efecto_de_fomento_al_turismo_sea_eficaz.pdf",
    "fragmento_numero": 34,
    "total_fragments_archivo": 37
  },
  {
    "archivo": "Que_factores_deben_acompanar_a_una_denominacion_de_origen_para_que_su_potencial_efecto_de_fomento_al_turismo_sea_eficaz.pdf",
    "fragmento_numero": 35,
    "total_fragments_archivo": 37
  },
  {
    "archivo": "Que_factores_deben_acompanar_a_una_denominacion_de_origen_para_que_su_potencial_efecto_de_fomento_al_turismo_sea_eficaz.pdf",
    "fragmento_numero": 36,
    "total_fragments_archivo": 37
  },
  {
    "archivo": "Que_factores_deben_acompanar_a_una_denominacion_de_origen_para_que_su_potencial_efecto_de_fomento_al_turismo_sea_eficaz.pdf",
    "fragmento_numero": 37,
    "total_fragments_archivo": 37
  },
  {
    "archivo": "RENL50P438.pdf",
    "fragmento_numero": 1,
    "total_fragments_archivo": 14
  },
  {
    "archivo": "RENL50P438.pdf",
    "fragmento_numero": 2,
    "total_fragments_archivo": 14
  },
  {
    "archivo": "RENL50P438.pdf",
    "fragmento_numero": 3,
    "total_fragments_archivo": 14
  },
  {
    "archivo": "RENL50P438.pdf",
    "fragmento_numero": 4,
    "total_fragments_archivo": 14
  },
  {
    "archivo": "RENL50P438.pdf",
    "fragmento_numero": 5,
    "total_fragments_archivo": 14
  },
  {
    "archivo": "RENL50P438.pdf",
    "fragmento_numero": 6,
    "total_fragments_archivo": 14
  },
  {
    "archivo": "RENL50P438.pdf",
    "fragmento_numero": 7,
    "total_fragments_archivo": 14
  },
  {
    "archivo": "RENL50P438.pdf",
    "fragmento_numero": 8,
    "total_fragments_archivo": 14
  },
  {
    "archivo": "RENL50P438.pdf",
    "fragmento_numero": 9,
    "total_fragments_archivo": 14
  },
  {
    "archivo": "RENL50P438.pdf",
    "fragmento_numero": 10,
    "total_fragments_archivo": 14
  },
  {
    "archivo": "RENL50P438.pdf",
    "fragmento_numero": 11,
    "total_fragments_archivo": 14
  },
  {
    "archivo": "RENL50P438.pdf",
    "fragmento_numero": 12,
    "total_fragments_archivo": 14
  },
  {
    "archivo": "RENL50P438.pdf",
    "fragmento_numero": 13,
    "total_fragments_archivo": 14
  },
  {
    "archivo": "RENL50P438.pdf",
    "fragmento_numero": 14,
    "total_fragments_archivo": 14
  },
  {
    "archivo": "reyes_o (1).pdf",
    "fragmento_numero": 1,
    "total_fragments_archivo": 31
  },
  {
    "archivo": "reyes_o (1).pdf",
    "fragmento_numero": 2,
    "total_fragments_archivo": 31
  },
  {
    "archivo": "reyes_o (1).pdf",
    "fragmento_numero": 3,
    "total_fragments_archivo": 31
  },
  {
    "archivo": "reyes_o (1).pdf",
    "fragmento_numero": 4,
    "total_fragments_archivo": 31
  },
  {
    "archivo": "reyes_o (1).pdf",
    "fragmento_numero": 5,
    "total_fragments_archivo": 31
  },
  {
    "archivo": "reyes_o (1).pdf",
    "fragmento_numero": 6,
    "total_fragments_archivo": 31
  },
  {
    "archivo": "reyes_o (1).pdf",
    "fragmento_numero": 7,
    "total_fragments_archivo": 31
  },
  {
    "archivo": "reyes_o (1).pdf",
    "fragmento_numero": 8,
    "total_fragments_archivo": 31
  },
  {
    "archivo": "reyes_o (1).pdf",
    "fragmento_numero": 9,
    "total_fragments_archivo": 31
  },
  {
    "archivo": "reyes_o (1).pdf",
    "fragmento_numero": 10,
    "total_fragments_archivo": 31
  },
  {
    "archivo": "reyes_o (1).pdf",
    "fragmento_numero": 11,
    "total_fragments_archivo": 31
  },
  {
    "archivo": "reyes_o (1).pdf",
    "fragmento_numero": 12,
    "total_fragments_archivo": 31
  },
  {
    "archivo": "reyes_o (1).pdf",
    "fragmento_numero": 13,
    "total_fragments_archivo": 31
  },
  {
    "archivo": "reyes_o (1).pdf",
    "fragmento_numero": 14,
    "total_fragments_archivo": 31
  },
  {
    "archivo": "reyes_o (1).pdf",
    "fragmento_numero": 15,
    "total_fragments_archivo": 31
  },
  {
    "archivo": "reyes_o (1).pdf",
    "fragmento_numero": 16,
    "total_fragments_archivo": 31
  },
  {
    "archivo": "reyes_o (1).pdf",
    "fragmento_numero": 17,
    "total_fragments_archivo": 31
  },
  {
    "archivo": "reyes_o (1).pdf",
    "fragmento_numero": 18,
    "total_fragments_archivo": 31
  },
  {
    "archivo": "reyes_o (1).pdf",
    "fragmento_numero": 19,
    "total_fragments_archivo": 31
  },
  {
    "archivo": "reyes_o (1).pdf",
    "fragmento_numero": 20,
    "total_fragments_archivo": 31
  },
  {
    "archivo": "reyes_o (1).pdf",
    "fragmento_numero": 21,
    "total_fragments_archivo": 31
  },
  {
    "archivo": "reyes_o (1).pdf",
    "fragmento_numero": 22,
    "total_fragments_archivo": 31
  },
  {
    "archivo": "reyes_o (1).pdf",
    "fragmento_numero": 23,
    "total_fragments_archivo": 31
  },
  {
    "archivo": "reyes_o (1).pdf",
    "fragmento_numero": 24,
    "total_fragments_archivo": 31
  },
  {
    "archivo": "reyes_o (1).pdf",
    "fragmento_numero": 25,
    "total_fragments_archivo": 31
  },
  {
    "archivo": "reyes_o (1).pdf",
    "fragmento_numero": 26,
    "total_fragments_archivo": 31
  },
  {
    "archivo": "reyes_o (1).pdf",
    "fragmento_numero": 27,
    "total_fragments_archivo": 31
  },
  {
    "archivo": "reyes_o (1).pdf",
    "fragmento_numero": 28,
    "total_fragments_archivo": 31
  },
  {
    "archivo": "reyes_o (1).pdf",
    "fragmento_numero": 29,
    "total_fragments_archivo": 31
  },
  {
    "archivo": "reyes_o (1).pdf",
    "fragmento_numero": 30,
    "total_fragments_archivo": 31
  },
  {
    "archivo": "reyes_o (1).pdf",
    "fragmento_numero": 31,
    "total_fragments_archivo": 31
  },
  {
    "archivo": "reyes_o.pdf",
    "fragmento_numero": 1,
    "total_fragments_archivo": 31
  },
  {
    "archivo": "reyes_o.pdf",
    "fragmento_numero": 2,
    "total_fragments_archivo": 31
  },
  {
    "archivo": "reyes_o.pdf",
    "fragmento_numero": 3,
    "total_fragments_archivo": 31
  },
  {
    "archivo": "reyes_o.pdf",
    "fragmento_numero": 4,
    "total_fragments_archivo": 31
  },
  {
    "archivo": "reyes_o.pdf",
    "fragmento_numero": 5,
    "total_fragments_archivo": 31
  },
  {
    "archivo": "reyes_o.pdf",
    "fragmento_numero": 6,
    "total_fragments_archivo": 31
  },
  {
    "archivo": "reyes_o.pdf",
    "fragmento_numero": 7,
    "total_fragments_archivo": 31
  },
  {
    "archivo": "reyes_o.pdf",
    "fragmento_numero": 8,
    "total_fragments_archivo": 31
  },
  {
    "archivo": "reyes_o.pdf",
    "fragmento_numero": 9,
    "total_fragments_archivo": 31
  },
  {
    "archivo": "reyes_o.pdf",
    "fragmento_numero": 10,
    "total_fragments_archivo": 31
  },
  {
    "archivo": "reyes_o.pdf",
    "fragmento_numero": 11,
    "total_fragments_archivo": 31
  },
  {
    "archivo": "reyes_o.pdf",
    "fragmento_numero": 12,
    "total_fragments_archivo": 31
  },
  {
    "archivo": "reyes_o.pdf",
    "fragmento_numero": 13,
    "total_fragments_archivo": 31
  },
  {
    "archivo": "reyes_o.pdf",
    "fragmento_numero": 14,
    "total_fragments_archivo": 31
  },
  {
    "archivo": "reyes_o.pdf",
    "fragmento_numero": 15,
    "total_fragments_archivo": 31
  },
  {
    "archivo": "reyes_o.pdf",
    "fragmento_numero": 16,
    "total_fragments_archivo": 31
  },
  {
    "archivo": "reyes_o.pdf",
    "fragmento_numero": 17,
    "total_fragments_archivo": 31
  },
  {
    "archivo": "reyes_o.pdf",
    "fragmento_numero": 18,
    "total_fragments_archivo": 31
  },
  {
    "archivo": "reyes_o.pdf",
    "fragmento_numero": 19,
    "total_fragments_archivo": 31
  },
  {
    "archivo": "reyes_o.pdf",
    "fragmento_numero": 20,
    "total_fragments_archivo": 31
  },
  {
    "archivo": "reyes_o.pdf",
    "fragmento_numero": 21,
    "total_fragments_archivo": 31
  },
  {
    "archivo": "reyes_o.pdf",
    "fragmento_numero": 22,
    "total_fragments_archivo": 31
  },
  {
    "archivo": "reyes_o.pdf",
    "fragmento_numero": 23,
    "total_fragments_archivo": 31
  },
  {
    "archivo": "reyes_o.pdf",
    "fragmento_numero": 24,
    "total_fragments_archivo": 31
  },
  {
    "archivo": "reyes_o.pdf",
    "fragmento_numero": 25,
    "total_fragments_archivo": 31
  },
  {
    "archivo": "reyes_o.pdf",
    "fragmento_numero": 26,
    "total_fragments_archivo": 31
  },
  {
    "archivo": "reyes_o.pdf",
    "fragmento_numero": 27,
    "total_fragments_archivo": 31
  },
  {
    "archivo": "reyes_o.pdf",
    "fragmento_numero": 28,
    "total_fragments_archivo": 31
  },
  {
    "archivo": "reyes_o.pdf",
    "fragmento_numero": 29,
    "total_fragments_archivo": 31
  },
  {
    "archivo": "reyes_o.pdf",
    "fragmento_numero": 30,
    "total_fragments_archivo": 31
  },
  {
    "archivo": "reyes_o.pdf",
    "fragmento_numero": 31,
    "total_fragments_archivo": 31
  },
  {
    "archivo": "Tesis - Juan Andrés Cubillos Peñailillo.pdf",
    "fragmento_numero": 1,
    "total_fragments_archivo": 27
  },
  {
    "archivo": "Tesis - Juan Andrés Cubillos Peñailillo.pdf",
    "fragmento_numero": 2,
    "total_fragments_archivo": 27
  },
  {
    "archivo": "Tesis - Juan Andrés Cubillos Peñailillo.pdf",
    "fragmento_numero": 3,
    "total_fragments_archivo": 27
  },
  {
    "archivo": "Tesis - Juan Andrés Cubillos Peñailillo.pdf",
    "fragmento_numero": 4,
    "total_fragments_archivo": 27
  },
  {
    "archivo": "Tesis - Juan Andrés Cubillos Peñailillo.pdf",
    "fragmento_numero": 5,
    "total_fragments_archivo": 27
  },
  {
    "archivo": "Tesis - Juan Andrés Cubillos Peñailillo.pdf",
    "fragmento_numero": 6,
    "total_fragments_archivo": 27
  },
  {
    "archivo": "Tesis - Juan Andrés Cubillos Peñailillo.pdf",
    "fragmento_numero": 7,
    "total_fragments_archivo": 27
  },
  {
    "archivo": "Tesis - Juan Andrés Cubillos Peñailillo.pdf",
    "fragmento_numero": 8,
    "total_fragments_archivo": 27
  },
  {
    "archivo": "Tesis - Juan Andrés Cubillos Peñailillo.pdf",
    "fragmento_numero": 9,
    "total_fragments_archivo": 27
  },
  {
    "archivo": "Tesis - Juan Andrés Cubillos Peñailillo.pdf",
    "fragmento_numero": 10,
    "total_fragments_archivo": 27
  },
  {
    "archivo": "Tesis - Juan Andrés Cubillos Peñailillo.pdf",
    "fragmento_numero": 11,
    "total_fragments_archivo": 27
  },
  {
    "archivo": "Tesis - Juan Andrés Cubillos Peñailillo.pdf",
    "fragmento_numero": 12,
    "total_fragments_archivo": 27
  },
  {
    "archivo": "Tesis - Juan Andrés Cubillos Peñailillo.pdf",
    "fragmento_numero": 13,
    "total_fragments_archivo": 27
  },
  {
    "archivo": "Tesis - Juan Andrés Cubillos Peñailillo.pdf",
    "fragmento_numero": 14,
    "total_fragments_archivo": 27
  },
  {
    "archivo": "Tesis - Juan Andrés Cubillos Peñailillo.pdf",
    "fragmento_numero": 15,
    "total_fragments_archivo": 27
  },
  {
    "archivo": "Tesis - Juan Andrés Cubillos Peñailillo.pdf",
    "fragmento_numero": 16,
    "total_fragments_archivo": 27
  },
  {
    "archivo": "Tesis - Juan Andrés Cubillos Peñailillo.pdf",
    "fragmento_numero": 17,
    "total_fragments_archivo": 27
  },
  {
    "archivo": "Tesis - Juan Andrés Cubillos Peñailillo.pdf",
    "fragmento_numero": 18,
    "total_fragments_archivo": 27
  },
  {
    "archivo": "Tesis - Juan Andrés Cubillos Peñailillo.pdf",
    "fragmento_numero": 19,
    "total_fragments_archivo": 27
  },
  {
    "archivo": "Tesis - Juan Andrés Cubillos Peñailillo.pdf",
    "fragmento_numero": 20,
    "total_fragments_archivo": 27
  },
  {
    "archivo": "Tesis - Juan Andrés Cubillos Peñailillo.pdf",
    "fragmento_numero": 21,
    "total_fragments_archivo": 27
  },
  {
    "archivo": "Tesis - Juan Andrés Cubillos Peñailillo.pdf",
    "fragmento_numero": 22,
    "total_fragments_archivo": 27
  },
  {
    "archivo": "Tesis - Juan Andrés Cubillos Peñailillo.pdf",
    "fragmento_numero": 23,
    "total_fragments_archivo": 27
  },
  {
    "archivo": "Tesis - Juan Andrés Cubillos Peñailillo.pdf",
    "fragmento_numero": 24,
    "total_fragments_archivo": 27
  },
  {
    "archivo": "Tesis - Juan Andrés Cubillos Peñailillo.pdf",
    "fragmento_numero": 25,
    "total_fragments_archivo": 27
  },
  {
    "archivo": "Tesis - Juan Andrés Cubillos Peñailillo.pdf",
    "fragmento_numero": 26,
    "total_fragments_archivo": 27
  },
  {
    "archivo": "Tesis - Juan Andrés Cubillos Peñailillo.pdf",
    "fragmento_numero": 27,
    "total_fragments_archivo": 27
  },
  {
    "archivo": "أيمن.pdf",
    "fragmento_numero": 1,
    "total_fragments_archivo": 16
  },
  {
    "archivo": "أيمن.pdf",
    "fragmento_numero": 2,
    "total_fragments_archivo": 16
  },
  {
    "archivo": "أيمن.pdf",
    "fragmento_numero": 3,
    "total_fragments_archivo": 16
  },
  {
    "archivo": "أيمن.pdf",
    "fragmento_numero": 4,
    "total_fragments_archivo": 16
  },
  {
    "archivo": "أيمن.pdf",
    "fragmento_numero": 5,
    "total_fragments_archivo": 16
  },
  {
    "archivo": "أيمن.pdf",
    "fragmento_numero": 6,
    "total_fragments_archivo": 16
  },
  {
    "archivo": "أيمن.pdf",
    "fragmento_numero": 7,
    "total_fragments_archivo": 16
  },
  {
    "archivo": "أيمن.pdf",
    "fragmento_numero": 8,
    "total_fragments_archivo": 16
  },
  {
    "archivo": "أيمن.pdf",
    "fragmento_numero": 9,
    "total_fragments_archivo": 16
  },
  {
    "archivo": "أيمن.pdf",
    "fragmento_numero": 10,
    "total_fragments_archivo": 16
  },
  {
    "archivo": "أيمن.pdf",
    "fragmento_numero": 11,
    "total_fragments_archivo": 16
  },
  {
    "archivo": "أيمن.pdf",
    "fragmento_numero": 12,
    "total_fragments_archivo": 16
  },
  {
    "archivo": "أيمن.pdf",
    "fragmento_numero": 13,
    "total_fragments_archivo": 16
  },
  {
    "archivo": "أيمن.pdf",
    "fragmento_numero": 14,
    "total_fragments_archivo": 16
  },
  {
    "archivo": "أيمن.pdf",
    "fragmento_numero": 15,
    "total_fragments_archivo": 16
  },
  {
    "archivo": "أيمن.pdf",
    "fragmento_numero": 16,
    "total_fragments_archivo": 16
  }
]